{
  "version": 1,
  "state": {
    "created_at": 1771460922.2460523,
    "last_save_time": 1771488195.1321032,
    "total_records": 1,
    "total_evaluations": 1
  },
  "history": [
    {
      "id": "991d0ba2-f583-40f7-8764-ab4d3bd60b09",
      "timestamp": 1771460916.6934483,
      "timestamp_str": "02-19 08:28:36",
      "exit_price": 66333.0425,
      "direction": "SHORT",
      "reason": "TAKE_PROFIT",
      "bar_idx_at_exit": 502,
      "detail": {
        "close_reason": "TAKE_PROFIT",
        "original_sl": 68393.4865417766,
        "template_fingerprint": "",
        "market_regime": "震荡偏空"
      },
      "entry_price": 68121.00253165,
      "entry_atr": 47.600000000001664,
      "sl_price": 68393.4865417766,
      "tp_price": 67739.52491747275,
      "sl_distance_pct": 0.4,
      "tp_distance_pct": 0.56,
      "sl_atr_multiple": 5.72,
      "tp_atr_multiple": 8.01,
      "profit_pct": 103.43,
      "peak_profit_pct": 52.75,
      "hold_bars": 502,
      "trailing_stage": 0,
      "evaluated": true,
      "price_after_eval": 66705.5,
      "bars_waited": 30,
      "move_pct": -0.5615,
      "outcome": "correct",
      "evaluation_time": 1771479241.3426292
    }
  ],
  "pending": [],
  "scores": {
    "TAKE_PROFIT": {
      "reason": "TAKE_PROFIT",
      "correct": 1,
      "too_tight": 0,
      "neutral": 0,
      "total": 1,
      "accuracy": 1.0,
      "recent_trend": 0.5,
      "total_missed_pct": 0.0,
      "total_saved_pct": 0.56
    }
  }
}